setup.py
redis_graph/__init__.py
redis_graph.egg-info/PKG-INFO
redis_graph.egg-info/SOURCES.txt
redis_graph.egg-info/dependency_links.txt
redis_graph.egg-info/top_level.txt
test/__init__.py
test/test_redis_graph.py