Metadata-Version: 1.0
Name: redis_graph
Version: 1.0
Summary: Python graph database implemented on top of Redis.
Home-page: http://www.amix.dk/
Author: amix
Author-email: amix@amix.dk
License: BSD
Keywords: redis graph database
Platform: Any
Classifier: Development Status :: 4 - Beta
Classifier: Intended Audience :: Developers
Classifier: License :: OSI Approved :: BSD License
Classifier: Operating System :: OS Independent
Classifier: Programming Language :: Python
Classifier: Topic :: Software Development :: Libraries :: Python Modules
